{
  "ID": "a12a8ca5-d9ab-47a8-a92f-9c5c5a96a1e3",
  "Version": "3.10.0.0",
  "Name": "leftTop",
  "Content": {
    "Content": {
      "Animation": {
        "Duration": 0,
        "Speed": 1.0,
        "Timelines": [],
        "ctype": "TimelineActionData"
      },
      "AnimationList": [],
      "ObjectData": {
        "Tag": 440,
        "Children": [
          {
            "FontSize": 25,
            "LabelText": "1234567",
            "OutlineColor": {
              "G": 0,
              "B": 0
            },
            "ShadowColor": {
              "R": 110,
              "G": 110,
              "B": 110
            },
            "ShadowOffsetX": 2.0,
            "ShadowOffsetY": -2.0,
            "AnchorPoint": {
              "ScaleY": 0.5
            },
            "Position": {
              "X": 470.687,
              "Y": 375.3744
            },
            "Scale": {
              "ScaleX": 1.1483,
              "ScaleY": 1.0
            },
            "CColor": {
              "R": 136,
              "G": 96,
              "B": 9
            },
            "IconVisible": false,
            "PrePosition": {
              "X": 0.4143,
              "Y": 0.5865
            },
            "PreSize": {
              "X": 0.0801,
              "Y": 0.0391
            },
            "LeftMargin": 470.687,
            "RightMargin": 574.313,
            "TopMargin": 252.1256,
            "BottomMargin": 362.8744,
            "Tag": 441,
            "ActionTag": -192803878,
            "Size": {
              "X": 91.0,
              "Y": 25.0
            },
            "Name": "roomId",
            "ctype": "TextObjectData"
          },
          {
            "FontSize": 25,
            "LabelText": "10/99",
            "HorizontalAlignmentType": "HT_Center",
            "VerticalAlignmentType": "VT_Center",
            "OutlineColor": {
              "G": 0,
              "B": 0
            },
            "ShadowColor": {
              "R": 110,
              "G": 110,
              "B": 110
            },
            "ShadowOffsetX": 2.0,
            "ShadowOffsetY": -2.0,
            "AnchorPoint": {
              "ScaleX": 0.5,
              "ScaleY": 0.5
            },
            "Position": {
              "X": 673.0187,
              "Y": 373.3744
            },
            "Scale": {
              "ScaleX": 1.0,
              "ScaleY": 1.0
            },
            "CColor": {
              "R": 136,
              "G": 96,
              "B": 9
            },
            "IconVisible": false,
            "PrePosition": {
              "X": 0.5924,
              "Y": 0.5834
            },
            "PreSize": {
              "X": 0.0572,
              "Y": 0.0391
            },
            "LeftMargin": 640.5187,
            "RightMargin": 430.4813,
            "TopMargin": 254.1256,
            "BottomMargin": 360.8744,
            "Tag": 442,
            "ActionTag": 857049736,
            "Size": {
              "X": 65.0,
              "Y": 25.0
            },
            "Name": "roomId_0",
            "ctype": "TextObjectData"
          },
          {
            "IsCustomSize": true,
            "FontSize": 20,
            "LabelText": "三胡一墩:100000000000000",
            "HorizontalAlignmentType": "HT_Center",
            "VerticalAlignmentType": "VT_Center",
            "OutlineColor": {
              "G": 0,
              "B": 0
            },
            "ShadowColor": {
              "R": 110,
              "G": 110,
              "B": 110
            },
            "ShadowOffsetX": 2.0,
            "ShadowOffsetY": -2.0,
            "AnchorPoint": {
              "ScaleX": 0.5,
              "ScaleY": 0.5
            },
            "Position": {
              "X": 568.0001,
              "Y": 337.4204
            },
            "Scale": {
              "ScaleX": 1.0,
              "ScaleY": 1.0
            },
            "CColor": {
              "R": 136,
              "G": 96,
              "B": 9
            },
            "IconVisible": false,
            "PrePosition": {
              "X": 0.5,
              "Y": 0.5272
            },
            "PreSize": {
              "X": 1.0,
              "Y": 0.0469
            },
            "LeftMargin": 0.0001,
            "RightMargin": -0.0001,
            "TopMargin": 287.5796,
            "BottomMargin": 322.4204,
            "Tag": 443,
            "ActionTag": -1627507187,
            "Size": {
              "X": 1136.0,
              "Y": 30.0
            },
            "Name": "des",
            "ctype": "TextObjectData"
          },
          {
            "FileData": {
              "Type": "Normal",
              "Path": "chenzhouzipai.png",
              "Plist": ""
            },
            "Scale9OriginX": 76,
            "Scale9OriginY": 19,
            "Scale9Width": 79,
            "Scale9Height": 21,
            "AnchorPoint": {
              "ScaleX": 0.5,
              "ScaleY": 0.5
            },
            "Position": {
              "X": 568.0001,
              "Y": 428.18
            },
            "Scale": {
              "ScaleX": 1.0,
              "ScaleY": 1.0
            },
            "CColor": {},
            "IconVisible": false,
            "PrePosition": {
              "X": 0.5,
              "Y": 0.669
            },
            "PreSize": {
              "X": 0.2033,
              "Y": 0.0922
            },
            "LeftMargin": 452.5001,
            "RightMargin": 452.4999,
            "TopMargin": 182.32,
            "BottomMargin": 398.68,
            "Tag": 92,
            "ActionTag": 1473146263,
            "Size": {
              "X": 231.0,
              "Y": 59.0
            },
            "Name": "title",
            "ctype": "ImageViewObjectData"
          },
          {
            "FileData": {
              "Type": "Normal",
              "Path": "fangjianhao.png",
              "Plist": ""
            },
            "Scale9OriginX": 34,
            "Scale9OriginY": 10,
            "Scale9Width": 37,
            "Scale9Height": 13,
            "AnchorPoint": {
              "ScaleX": 0.5,
              "ScaleY": 0.5
            },
            "Position": {
              "X": 416.337,
              "Y": 375.3749
            },
            "Scale": {
              "ScaleX": 1.0,
              "ScaleY": 1.0
            },
            "CColor": {},
            "IconVisible": false,
            "PrePosition": {
              "X": 0.3665,
              "Y": 0.5865
            },
            "PreSize": {
              "X": 0.0924,
              "Y": 0.0516
            },
            "LeftMargin": 363.837,
            "RightMargin": 667.163,
            "TopMargin": 248.1251,
            "BottomMargin": 358.8749,
            "Tag": 93,
            "ActionTag": 645926222,
            "Size": {
              "X": 105.0,
              "Y": 33.0
            },
            "Name": "Image_4",
            "ctype": "ImageViewObjectData"
          },
          {
            "FileData": {
              "Type": "Normal",
              "Path": "jiju_zi.png",
              "Plist": ""
            },
            "Scale9OriginX": 41,
            "Scale9OriginY": 9,
            "Scale9Width": 43,
            "Scale9Height": 12,
            "AnchorPoint": {
              "ScaleX": 0.5,
              "ScaleY": 0.5
            },
            "Position": {
              "X": 674.7932,
              "Y": 374.3746
            },
            "Scale": {
              "ScaleX": 1.0,
              "ScaleY": 1.0
            },
            "CColor": {},
            "IconVisible": false,
            "PrePosition": {
              "X": 0.594,
              "Y": 0.585
            },
            "PreSize": {
              "X": 0.11,
              "Y": 0.0469
            },
            "LeftMargin": 612.2932,
            "RightMargin": 398.7068,
            "TopMargin": 250.6254,
            "BottomMargin": 359.3746,
            "Tag": 94,
            "ActionTag": -1330319747,
            "Size": {
              "X": 125.0,
              "Y": 30.0
            },
            "Name": "Image_5",
            "ctype": "ImageViewObjectData"
          }
        ],
        "Size": {
          "X": 1136.0,
          "Y": 640.0
        },
        "Name": "Layer",
        "ctype": "LayerObjectData"
      },
      "UsedResources": [
        "chenzhouzipai.png",
        "fangjianhao.png",
        "jiju_zi.png"
      ],
      "ctype": "GameFileData"
    }
  },
  "Type": "Layer"
}